pyDEMATEL/DEMATELSolver.py
pyDEMATEL/DEMATELWindow.py
pyDEMATEL/FuzzyDEMATELSolver.py
pyDEMATEL/__init__.py
pyDEMATEL-0.2.2.dist-info/LICENSE.md
pyDEMATEL-0.2.2.dist-info/METADATA
pyDEMATEL-0.2.2.dist-info/WHEEL
pyDEMATEL-0.2.2.dist-info/entry_points.txt
pyDEMATEL-0.2.2.dist-info/top_level.txt
pyDEMATEL-0.2.2.dist-info/RECORD
