Metadata-Version: 2.1
Name: pyDEMATEL
Version: 0.2.2
Summary: pyDematel a python-based tool implementing the Dematel and fuzzy Dematel methods for improved decision making
Home-page: https://github.com/achekry/-Elsevier-SoftwareX-pyDEMATEL
Author: Abderrahman Chekry, Jamal Bakkas, Mohamed Hanin, Elizabeth Caro Montero, Mirtha Silvana Garat de Marin and Imran Ashraf
Author-email: a.chekry@uca.ac.ma
Classifier: Programming Language :: Python :: 3
Classifier: License :: OSI Approved :: BSD License
Classifier: Operating System :: OS Independent
Requires-Python: >=3.6
License-File: LICENSE.md
Requires-Dist: numpy >=1.22.0
Requires-Dist: matplotlib >=3.4.3
Requires-Dist: openpyxl >=3.0.9
